PyEncodeVis/__init__.py
PyEncodeVis/general_heatmap.py
PyEncodeVis/kmers_heatmap.py
PyEncodeVis-0.0.1.dist-info/METADATA
PyEncodeVis-0.0.1.dist-info/WHEEL
PyEncodeVis-0.0.1.dist-info/top_level.txt
PyEncodeVis-0.0.1.dist-info/RECORD
